{
  "users":[
    {
      "id":1,
      "name":"kiran",
      "address":"valsad",
      "email":"kiran@gmail.com"
    },
    {
      "id":2,
      "name":"jay",
      "address":"vapi",
      "email":"jay@gmail.com"
    },
    {
      "id":3,
      "name":"pinal",
      "address":"pune",
      "email":"pinal@gmail.com"
    },
    {
      "id":4,
      "name":"ketan",
      "address":"baroda",
      "email":"ketan@gmail.com"
    },
    {
      "id":5,
      "name":"abhi",
      "address":"navsari",
      "email":"abhi@gmail.com"
    },
    {
      "id":6,
      "name":"dhruv",
      "address":"maroli",
      "email":"dhruv@gmail.com"
    }
  ]
}
